can_weather_data/__init__.py
can_weather_data/weatherdata.py
can_weather_data-0.2.dist-info/LICENSE
can_weather_data-0.2.dist-info/METADATA
can_weather_data-0.2.dist-info/WHEEL
can_weather_data-0.2.dist-info/top_level.txt
can_weather_data-0.2.dist-info/RECORD
