Metadata-Version: 2.1
Name: can-weather-data
Version: 0.2
Summary: Weather Data From climate.weather.gc.ca
Home-page: https://github.com/DulminiGuruge/can_weather_data
Author: Dulmini Guruge
Author-email: dulminiguruge@gmail.com
License: MIT
Keywords: weather package climate data
Classifier: Programming Language :: Python :: 3
Classifier: License :: OSI Approved :: MIT License
Classifier: Operating System :: OS Independent
License-File: LICENSE
Requires-Dist: pandas
Requires-Dist: numpy
Requires-Dist: python-dateutil
Requires-Dist: env-canada
Requires-Dist: nest-asyncio
